elfi/__init__.py
elfi/client.py
elfi/compiler.py
elfi/executor.py
elfi/loader.py
elfi/store.py
elfi/utils.py
elfi/clients/__init__.py
elfi/clients/dask.py
elfi/clients/ipyparallel.py
elfi/clients/multiprocessing.py
elfi/clients/native.py
elfi/examples/__init__.py
elfi/examples/ar1.py
elfi/examples/arch.py
elfi/examples/bdm.py
elfi/examples/bignk.py
elfi/examples/daycare.py
elfi/examples/gauss.py
elfi/examples/gnk.py
elfi/examples/lorenz.py
elfi/examples/lotka_volterra.py
elfi/examples/ma2.py
elfi/examples/mg1.py
elfi/examples/ricker.py
elfi/examples/scratch_assay.py
elfi/examples/stochastic_volatility_model.py
elfi/examples/toad.py
elfi/examples/cpp/Makefile
elfi/examples/cpp/bdm.cpp
elfi/examples/cpp/example_input.txt
elfi/examples/cpp/example_output.txt
elfi/methods/__init__.py
elfi/methods/classifier.py
elfi/methods/density_ratio_estimation.py
elfi/methods/diagnostics.py
elfi/methods/mcmc.py
elfi/methods/model_selection.py
elfi/methods/post_processing.py
elfi/methods/posteriors.py
elfi/methods/results.py
elfi/methods/utils.py
elfi/methods/bo/__init__.py
elfi/methods/bo/acquisition.py
elfi/methods/bo/gpy_regression.py
elfi/methods/bo/utils.py
elfi/methods/bsl/__init__.py
elfi/methods/bsl/cov_warton.py
elfi/methods/bsl/gaussian_copula_density.py
elfi/methods/bsl/gaussian_rank_corr.py
elfi/methods/bsl/pdf_methods.py
elfi/methods/bsl/pre_sample_methods.py
elfi/methods/bsl/slice_gamma_mean.py
elfi/methods/bsl/slice_gamma_variance.py
elfi/methods/inference/__init__.py
elfi/methods/inference/bolfi.py
elfi/methods/inference/bolfire.py
elfi/methods/inference/bsl.py
elfi/methods/inference/parameter_inference.py
elfi/methods/inference/romc.py
elfi/methods/inference/samplers.py
elfi/model/__init__.py
elfi/model/augmenter.py
elfi/model/elfi_model.py
elfi/model/extensions.py
elfi/model/graphical_model.py
elfi/model/tools.py
elfi/model/utils.py
elfi/testbench/__init__.py
elfi/testbench/testbench.py
elfi/visualization/__init__.py
elfi/visualization/interactive.py
elfi-0.8.7.dist-info/LICENSE
elfi-0.8.7.dist-info/METADATA
elfi-0.8.7.dist-info/WHEEL
elfi-0.8.7.dist-info/top_level.txt
elfi-0.8.7.dist-info/RECORD
