Metadata-Version: 2.1
Name: elfi
Version: 0.8.7
Summary: ELFI - Engine for Likelihood-free Inference
Home-page: http://elfi.readthedocs.io
Author: ELFI authors
Author-email: elfi-support@hiit.fi
License: BSD
Keywords: abc likelihood-free statistics
Platform: UNKNOWN
Classifier: Programming Language :: Python :: 3.7
Classifier: Topic :: Scientific/Engineering
Classifier: Topic :: Scientific/Engineering :: Artificial Intelligence
Classifier: Topic :: Scientific/Engineering :: Bio-Informatics
Classifier: Topic :: Scientific/Engineering :: Mathematics
Classifier: Operating System :: OS Independent
Classifier: Development Status :: 4 - Beta
Classifier: Intended Audience :: Science/Research
Classifier: License :: OSI Approved :: BSD License
Requires-Dist: dask[distributed] (>=2.30.0)
Requires-Dist: numpy (<=1.24.4,>=1.12.1)
Requires-Dist: scipy (>=0.19)
Requires-Dist: matplotlib (>=1.1)
Requires-Dist: GPy (>=1.0.9)
Requires-Dist: networkX (>=2.0)
Requires-Dist: ipyparallel (>=6)
Requires-Dist: toolz (>=0.8)
Requires-Dist: scikit-learn (>=0.18.1)
Requires-Dist: numdifftools (>=0.9)
Provides-Extra: doc
Requires-Dist: Sphinx ; extra == 'doc'
Provides-Extra: graphviz
Requires-Dist: graphviz (>=0.7.1) ; extra == 'graphviz'
